bpy/__init__.py
bpy/context.py
bpy/ops.py
bpy/path.py
bpy/props.py
bpy/types.py
bpy/utils.py
pumpkinpy/__init__.py
pumpkinpy/logic.py
pumpkinpy/algorithms/__init__.py
pumpkinpy/algorithms/sorting.py
pumpkinpy/app/__init__.py
pumpkinpy/app/graphical_anim/__init__.py
pumpkinpy/app/graphical_anim/errors.py
pumpkinpy/app/graphical_anim/scene.py
pumpkinpy/app/graphical_anim/shapes.py
pumpkinpy/app/rubiks_cube/__init__.py
pumpkinpy/app/rubiks_cube/two_by_two.py
pumpkinpy/colorutils/__init__.py
pumpkinpy/colorutils/conversions.py
pumpkinpy/data/__init__.py
pumpkinpy/data/files.py
pumpkinpy/imageutils/__init__.py
pumpkinpy/imageutils/_utils.py
pumpkinpy/imageutils/filters.py
pumpkinpy/imageutils/transformations.py
pumpkinpy/imageutils/types.py
pumpkinpy/mathlib/__init__.py
pumpkinpy/mathlib/numtheory.py
pumpkinpy/pygame_interface/__init__.py
pumpkinpy/pygame_interface/elements/__init__.py
pumpkinpy/pygame_interface/elements/buttons.py
pumpkinpy/pygameutils/__init__.py
pumpkinpy/pygameutils/backgrounds.py
pumpkinpy/pygameutils/elements.py
pumpkinpy/pygameutils/errors.py
pumpkinpy/pygameutils/interface/__init__.py
pumpkinpy/pygameutils/interface/props.py
pumpkinpy/socketutils/__init__.py
pumpkinpy/socketutils/functions.py
pumpkinpy/socketutils/networks/__init__.py
pumpkinpy/socketutils/networks/general.py
pumpkinpy/view3d/__init__.py
pumpkinpy/view3d/cameras.py
pumpkinpy/view3d/elements.py
pumpkinpy-0.4.4.dist-info/LICENSE
pumpkinpy-0.4.4.dist-info/METADATA
pumpkinpy-0.4.4.dist-info/WHEEL
pumpkinpy-0.4.4.dist-info/top_level.txt
pumpkinpy-0.4.4.dist-info/RECORD
