Metadata-Version: 2.1
Name: pumpkinpy
Version: 0.4.4
Summary: A Python module with utilities for many fields.
Home-page: https://github.com/Spatial-Innovations/PumpkinPy
Author: Spatial Innovations
Author-email: spatialinnovations@gmail.com
License: UNKNOWN
Platform: UNKNOWN
Classifier: Programming Language :: Python :: 3
Classifier: License :: OSI Approved :: GNU General Public License v2 or later (GPLv2+)
Classifier: Operating System :: OS Independent
Requires-Dist: pygame
Requires-Dist: numpy
Requires-Dist: pillow
Requires-Dist: opencv-python
